[
  {
    "date": "2026-07-01",
    "time": "09:05",
    "name": "פין פלדה מקצועי להוספת משקל למכונות כושר - Gym Pin",
    "category": "ספורט וכושר",
    "url": "https://konimbezol.co.il/product/gym-weight-stack-loading-pin-adapter",
    "link": "https://s.click.aliexpress.com/e/_c4eNNgsz"
  },
  {
    "date": "2026-07-01",
    "time": "09:20",
    "name": "ADDIESDIVE שעון צלילה לגברים AD2545 עם ספיר וחוגה זוהרת",
    "category": "שעונים ותכשיטים",
    "url": "https://konimbezol.co.il/product/addiesdive-ad2545-mens-dive-watch",
    "link": "https://s.click.aliexpress.com/e/_c3Q10EZR"
  },
  {
    "date": "2026-07-01",
    "time": "09:35",
    "name": "שרשרת אופניים מקצועית 6-11 הילוכים MTB/שטח",
    "category": "ספורט וכושר",
    "url": "https://konimbezol.co.il/product/professional-bike-chain-6-11-speed-mtb-road",
    "link": "https://s.click.aliexpress.com/e/_c4Pj3pz3"
  },
  {
    "date": "2026-07-01",
    "time": "09:48",
    "name": "מגן מזיקה והתזה מנירוסטה למיקסר KitchenAid",
    "category": "שעונים ותכשיטים",
    "url": "https://konimbezol.co.il/product/kitchenaid-mixer-stainless-steel-pouring-shield-guard",
    "link": "https://s.click.aliexpress.com/e/_c3ytl9VT"
  },
  {
    "date": "2026-07-01",
    "time": "10:05",
    "name": "לוח שכיבות סמיכה רב-תכליתי מתקפל עם רצועות התנגדות",
    "category": "ספורט וכושר",
    "url": "https://konimbezol.co.il/product/portable-multifunctional-push-up-board-fitness-kit",
    "link": "https://s.click.aliexpress.com/e/_c3b4YsHn"
  },
  {
    "date": "2026-07-01",
    "time": "10:19",
    "name": "נעלי ריצה לנשים Nike FV8480-002 - דגם חדש ונושם",
    "category": "אופנה וסטייל",
    "url": "https://konimbezol.co.il/product/nike-womens-running-shoes-fv8480-002-review",
    "link": "https://s.click.aliexpress.com/e/_c2yvHeRj"
  },
  {
    "date": "2026-07-01",
    "time": "10:34",
    "name": "מעיל טרנץ' אדידס אוריג'ינלס לנשים Adidas IC5588",
    "category": "אופנה וסטייל",
    "url": "https://konimbezol.co.il/product/adidas-originals-women-trench-sport-coat-ic5588-review",
    "link": "https://s.click.aliexpress.com/e/_c3KzhYPF"
  },
  {
    "date": "2026-07-01",
    "time": "10:50",
    "name": "נעלי כדורסל Nike Jordan Zion 2 לגברים DM0858-367",
    "category": "אופנה וסטייל",
    "url": "https://konimbezol.co.il/product/nike-jordan-zion-2-basketball-shoes-dm0858-367-review",
    "link": "https://s.click.aliexpress.com/e/_c3gPOlLJ"
  },
  {
    "date": "2026-07-01",
    "time": "11:04",
    "name": "סט גומיות התנגדות לאימון כושר ביתי למתחילים",
    "category": "ספורט וכושר",
    "url": "https://konimbezol.co.il/product/resistance-fitness-bands-beginner-workout",
    "link": "https://s.click.aliexpress.com/e/_c41MjCP7"
  },
  {
    "date": "2026-07-01",
    "time": "11:19",
    "name": "טבעת פילאטיס מקצועית לחיטוב וחיזוק הגוף",
    "category": "שעונים ותכשיטים",
    "url": "https://konimbezol.co.il/product/professional-pilates-ring-toning-circle-workout",
    "link": "https://s.click.aliexpress.com/e/_c3MFCxt5"
  },
  {
    "date": "2026-07-01",
    "time": "11:34",
    "name": "ארגונית גדולה לרכב למושב האחורי/תא המטען – אוקספורד",
    "category": "מוצרים לרכב",
    "url": "https://konimbezol.co.il/product/car-trunk-organizer-oxford",
    "link": "https://s.click.aliexpress.com/e/_c4l7SVmp"
  },
  {
    "date": "2026-07-01",
    "time": "11:49",
    "name": "נעלי כדורסל Jordan Luka דגם HF0819-006 ג'ורדן לוקה",
    "category": "אופנה וסטייל",
    "url": "https://konimbezol.co.il/product/nike-jordan-luka-basketball-shoes-hf0819-006",
    "link": "https://s.click.aliexpress.com/e/_c3HWtmo5"
  },
  {
    "date": "2026-07-01",
    "time": "12:04",
    "name": "זוג גריפים סיליקון לעיבוי מוט משקולות ושיפור האחיזה",
    "category": "ספורט וכושר",
    "url": "https://konimbezol.co.il/product/fat-bar-grips-silicone-fitness-handle-grips-aliexpress",
    "link": "https://s.click.aliexpress.com/e/_c39JQKL3"
  },
  {
    "date": "2026-07-01",
    "time": "12:19",
    "name": "משאבת אופניים חשמלית מיני 100 PSI נטענת Type-C",
    "category": "ספורט וכושר",
    "url": "https://konimbezol.co.il/product/mini-electric-cycling-pump-100psi-rechargeable-type-c",
    "link": "https://s.click.aliexpress.com/e/_c4meM1Dj"
  },
  {
    "date": "2026-07-01",
    "time": "12:35",
    "name": "ברז מטבח חכם מבית Rozin עם מגע וחיישן",
    "category": "מוצרי מטבח",
    "url": "https://konimbezol.co.il/product/rozin-smart-touch-kitchen-faucet",
    "link": "https://s.click.aliexpress.com/e/_c4tAjtvF"
  },
  {
    "date": "2026-07-01",
    "time": "12:45",
    "name": "נעלי בית מבד פשתן יוניסקס לאביב-קיץ",
    "category": "שעונים ותכשיטים",
    "url": "https://konimbezol.co.il/product/linen-slippers-unisex-spring-summer",
    "link": "https://s.click.aliexpress.com/e/_c3zAEwMV"
  },
  {
    "date": "2026-07-01",
    "time": "12:49",
    "name": "גלגל בטן רחב ומקצועי לאימון ביתי עם מנגנון קפיץ חזרה",
    "category": "ספורט וכושר",
    "url": "https://konimbezol.co.il/product/pro-ab-roller-wheel-automatic-rebound-core-workout",
    "link": "https://s.click.aliexpress.com/e/_c3CHdXQN"
  },
  {
    "date": "2026-07-01",
    "time": "13:05",
    "name": "קפיץ יד מתכוונן 5-100 ק\"ג לחיזוק האמה וכוח האחיזה",
    "category": "גאדג'טים",
    "url": "https://konimbezol.co.il/product/adjustable-hand-gripper-5-100kg-forearm-strengthener",
    "link": "https://s.click.aliexpress.com/e/_c4eVUuNn"
  },
  {
    "date": "2026-07-01",
    "time": "13:20",
    "name": "גלאי מתכות נייד רגיש pinpointer II",
    "category": "גאדג'טים",
    "url": "https://konimbezol.co.il/product/2024-upgraded-metal-detector-pinpointer-ii-waterproof",
    "link": "https://s.click.aliexpress.com/e/_c3yBRKHf"
  }
]